typeform_advancedapi/TypeForm_AdvancedAPI.py
typeform_advancedapi/__init__.py
typeform_advancedapi-1.1.8.dist-info/LICENSE.txt
typeform_advancedapi-1.1.8.dist-info/METADATA
typeform_advancedapi-1.1.8.dist-info/WHEEL
typeform_advancedapi-1.1.8.dist-info/top_level.txt
typeform_advancedapi-1.1.8.dist-info/RECORD
