Metadata-Version: 2.1
Name: typeform-advancedapi
Version: 1.1.8
Summary: TypeForm API written in python
Home-page: https://github.com/kaiseranton/TypeForm_AdvancedAPI
Author: Anton Kaiser
Author-email: kaiser@kaiser.ovh
License: UNKNOWN
Platform: UNKNOWN
Classifier: Programming Language :: Python :: 3
Classifier: License :: OSI Approved :: MIT License
Classifier: Operating System :: OS Independent
Requires-Dist: requests (>=2.21.0)
